minigist/__init__.py
minigist/cli.py
minigist/config.py
minigist/constants.py
minigist/downloader.py
minigist/exceptions.py
minigist/logging.py
minigist/miniflux_client.py
minigist/models.py
minigist/notification.py
minigist/processor.py
minigist/pure_client.py
minigist/summarizer.py
minigist/pipeline/__init__.py
minigist/pipeline/base_worker.py
minigist/pipeline/fetch_worker.py
minigist/pipeline/llm_worker.py
minigist/pipeline/types.py
minigist/pipeline/update_worker.py
minigist-0.9.1.dist-info/licenses/LICENSE
minigist-0.9.1.dist-info/METADATA
minigist-0.9.1.dist-info/WHEEL
minigist-0.9.1.dist-info/entry_points.txt
minigist-0.9.1.dist-info/top_level.txt
minigist-0.9.1.dist-info/RECORD
