Metadata-Version: 2.4
Name: minigist
Version: 0.9.1
Summary: A tool that generates concise summaries for you Miniflux feeds.
Author: eikendev
Maintainer: eikendev
Project-URL: Homepage, https://github.com/eikendev/minigist
Keywords: miniflux,rss,feed,ai,summarization,cli
Classifier: Environment :: Console
Classifier: Programming Language :: Python :: 3
Classifier: Topic :: Internet :: WWW/HTTP :: Dynamic Content :: News/Diary
Classifier: Topic :: Text Processing :: Markup
Classifier: Topic :: Utilities
Requires-Python: >=3.13
License-File: LICENSE
Requires-Dist: apprise>=1.9.3
Requires-Dist: beautifulsoup4>=4.14.3
Requires-Dist: click>=8.1.8
Requires-Dist: httpx>=0.28.1
Requires-Dist: httpx-retries>=0.4.5
Requires-Dist: markdown>=3.8
Requires-Dist: miniflux>=1.1.3
Requires-Dist: nh3>=0.2.21
Requires-Dist: openai>=1.76.0
Requires-Dist: pydantic>=2.11.3
Requires-Dist: pyyaml>=6.0.2
Requires-Dist: structlog>=25.3.0
Requires-Dist: tenacity>=9.1.2
Requires-Dist: trafilatura>=2.0.0
Dynamic: license-file
